README.md
setup.cfg
setup.py
generic_job_queue/__init__.py
generic_job_queue.egg-info/PKG-INFO
generic_job_queue.egg-info/SOURCES.txt
generic_job_queue.egg-info/dependency_links.txt
generic_job_queue.egg-info/requires.txt
generic_job_queue.egg-info/top_level.txt
generic_job_queue/contracts/Job.py
generic_job_queue/contracts/JobHandler.py
generic_job_queue/contracts/JobQueue.py
generic_job_queue/contracts/__init__.py
generic_job_queue/enum/__init__.py
generic_job_queue/enum/job_status.py
generic_job_queue/model/JobLogger.py
generic_job_queue/model/JobPuller.py
generic_job_queue/model/__init__.py
generic_job_queue/model/sqlalchemy/SQLAlchemyJob.py
generic_job_queue/model/sqlalchemy/SQLAlchemyJobQueue.py
generic_job_queue/model/sqlalchemy/__init__.py
generic_job_queue/model/sqlalchemy/errors.py
generic_job_queue/model/sqlalchemy/orm/JobLogORM.py
generic_job_queue/model/sqlalchemy/orm/JobORM.py
generic_job_queue/model/sqlalchemy/orm/ORMBase.py
generic_job_queue/model/sqlalchemy/orm/__init__.py
generic_job_queue/model/sqlalchemy/orm/data_type.py