Metadata-Version: 1.1
Name: generic-job-queue
Version: 0.0.5
Summary: The generic job queue
Home-page: https://github.com/davidNHK/generic-job-queue
Author: David Ng
Author-email: david.ng.dev@gmail.com
License: BSD
Download-URL: https://github.com/davidNHK/generic-job-queue/archive/0.0.5.zip
Keywords: sqlalchemy,job queue,worker
Platform: UNKNOWN
